[
    {
        "id": 1,
        "first_name": "Rodina",
        "last_name": "Souttar",
        "email": "rsouttar0@phpbb.com",
        "password": "3JyKFs1wowK"
    },
    {
        "id": 2,
        "first_name": "Walliw",
        "last_name": "Laval",
        "email": "wlaval1@meetup.com",
        "password": "ikJfotG"
    },
    {
        "id": 3,
        "first_name": "Madonna",
        "last_name": "Leward",
        "email": "mleward2@shutterfly.com",
        "password": "oZ36Xgm"
    },
    {
        "id": 4,
        "first_name": "Sigfrid",
        "last_name": "Kincade",
        "email": "skincade3@symantec.com",
        "password": "Qj61VD"
    },
    {
        "id": 5,
        "first_name": "Cozmo",
        "last_name": "Londors",
        "email": "clondors4@google.cn",
        "password": "iGqzwjR1OmwT"
    },
    {
        "id": 6,
        "first_name": "Angele",
        "last_name": "Bermingham",
        "email": "abermingham5@plala.or.jp",
        "password": "DgJ0kTy"
    },
    {
        "id": 7,
        "first_name": "Kinnie",
        "last_name": "Benez",
        "email": "kbenez6@opera.com",
        "password": "9HPrfUA"
    },
    {
        "id": 8,
        "first_name": "Carmon",
        "last_name": "Merrick",
        "email": "cmerrick7@hao123.com",
        "password": "M8bDM6Wj"
    },
    {
        "id": 9,
        "first_name": "Jaquenette",
        "last_name": "Kinnon",
        "email": "jkinnon8@issuu.com",
        "password": "pn39MMeMv"
    },
    {
        "id": 10,
        "first_name": "Jeramie",
        "last_name": "Lumbly",
        "email": "jlumbly9@cam.ac.uk",
        "password": "FnVWpisUol"
    },
    {
        "id": 11,
        "first_name": "Cristine",
        "last_name": "Mundwell",
        "email": "cmundwella@yahoo.com",
        "password": "3GxyCtm"
    },
    {
        "id": 12,
        "first_name": "Ulysses",
        "last_name": "Parlour",
        "email": "uparlourb@phoca.cz",
        "password": "s0HBjVy"
    },
    {
        "id": 13,
        "first_name": "Kendell",
        "last_name": "Wasselin",
        "email": "kwasselinc@dedecms.com",
        "password": "8NnMBE"
    },
    {
        "id": 14,
        "first_name": "Geneva",
        "last_name": "Kaiser",
        "email": "gkaiserd@typepad.com",
        "password": "QBsxwxas"
    },
    {
        "id": 15,
        "first_name": "Cherie",
        "last_name": "Roycroft",
        "email": "croycrofte@webeden.co.uk",
        "password": "ON1vLEg6Ov"
    },
    {
        "id": 16,
        "first_name": "Katey",
        "last_name": "Christophe",
        "email": "kchristophef@jimdo.com",
        "password": "8Tz4a5o3lXi"
    },
    {
        "id": 17,
        "first_name": "Joy",
        "last_name": "Vautrey",
        "email": "jvautreyg@prnewswire.com",
        "password": "Js0h0IBDqrLB"
    },
    {
        "id": 18,
        "first_name": "Megan",
        "last_name": "Ure",
        "email": "mureh@berkeley.edu",
        "password": "2FsQbk"
    },
    {
        "id": 19,
        "first_name": "Fredia",
        "last_name": "Olivier",
        "email": "folivieri@sun.com",
        "password": "m0qt3U"
    },
    {
        "id": 20,
        "first_name": "Darill",
        "last_name": "Chugg",
        "email": "dchuggj@storify.com",
        "password": "UcnR6b0JaWy"
    },
    {
        "id": 21,
        "first_name": "Charley",
        "last_name": "Shergold",
        "email": "cshergoldk@usgs.gov",
        "password": "IOqRKQ3"
    },
    {
        "id": 22,
        "first_name": "Sofie",
        "last_name": "Wyett",
        "email": "swyettl@dmoz.org",
        "password": "YFD7C2dbwOz"
    },
    {
        "id": 23,
        "first_name": "Sarita",
        "last_name": "Tinton",
        "email": "stintonm@a8.net",
        "password": "PzzqLyoPvFhv"
    },
    {
        "id": 24,
        "first_name": "Richart",
        "last_name": "Luxen",
        "email": "rluxenn@techcrunch.com",
        "password": "aDumQJrcOGhF"
    },
    {
        "id": 25,
        "first_name": "Matthias",
        "last_name": "Harvie",
        "email": "mharvieo@biblegateway.com",
        "password": "x2Uyp30qU"
    },
    {
        "id": 26,
        "first_name": "Teddy",
        "last_name": "Ovenden",
        "email": "tovendenp@usa.gov",
        "password": "gLShb7OI5AV"
    },
    {
        "id": 27,
        "first_name": "Corissa",
        "last_name": "Zorzi",
        "email": "czorziq@aboutads.info",
        "password": "ON8gZtd9q"
    },
    {
        "id": 28,
        "first_name": "Caitlin",
        "last_name": "Millson",
        "email": "cmillsonr@flickr.com",
        "password": "qtQ8R3ZLIJ8"
    },
    {
        "id": 29,
        "first_name": "Tam",
        "last_name": "Greest",
        "email": "tgreests@topsy.com",
        "password": "wqVd4JuxD"
    },
    {
        "id": 30,
        "first_name": "Kristina",
        "last_name": "Semechik",
        "email": "ksemechikt@bloglovin.com",
        "password": "l2Kr8ZF3Ta"
    },
    {
        "id": 31,
        "first_name": "Rasia",
        "last_name": "Ganter",
        "email": "rganteru@sbwire.com",
        "password": "VHzxbCFCNN"
    },
    {
        "id": 32,
        "first_name": "Sasha",
        "last_name": "Casley",
        "email": "scasleyv@xinhuanet.com",
        "password": "yu4lQSE6Q"
    },
    {
        "id": 33,
        "first_name": "Gerhard",
        "last_name": "Lecky",
        "email": "gleckyw@is.gd",
        "password": "kJZ0deIyryR"
    },
    {
        "id": 34,
        "first_name": "Marika",
        "last_name": "Mallon",
        "email": "mmallonx@webnode.com",
        "password": "0SGD1XgGuP"
    },
    {
        "id": 35,
        "first_name": "Farrand",
        "last_name": "Elmer",
        "email": "felmery@cyberchimps.com",
        "password": "ehs5Qk"
    },
    {
        "id": 36,
        "first_name": "Brew",
        "last_name": "Klagges",
        "email": "bklaggesz@thetimes.co.uk",
        "password": "jmSfqcJV7W4"
    },
    {
        "id": 37,
        "first_name": "Vikky",
        "last_name": "Kaminski",
        "email": "vkaminski10@hugedomains.com",
        "password": "OjukZ99Jbz"
    },
    {
        "id": 38,
        "first_name": "Sara",
        "last_name": "Swepson",
        "email": "sswepson11@dailymotion.com",
        "password": "fWTeGu2R"
    },
    {
        "id": 39,
        "first_name": "Harlene",
        "last_name": "Clorley",
        "email": "hclorley12@amazon.co.jp",
        "password": "VdQnH9"
    },
    {
        "id": 40,
        "first_name": "Monro",
        "last_name": "Armytage",
        "email": "marmytage13@mlb.com",
        "password": "PHoBGH4"
    },
    {
        "id": 41,
        "first_name": "Darren",
        "last_name": "Stammler",
        "email": "dstammler14@state.tx.us",
        "password": "GNDLpHHnznbC"
    },
    {
        "id": 42,
        "first_name": "Bancroft",
        "last_name": "Ligerton",
        "email": "bligerton15@paginegialle.it",
        "password": "AvISYaJrM"
    },
    {
        "id": 43,
        "first_name": "Giorgia",
        "last_name": "Allsupp",
        "email": "gallsupp16@is.gd",
        "password": "ycCaEt"
    },
    {
        "id": 44,
        "first_name": "Germaine",
        "last_name": "Hadcock",
        "email": "ghadcock17@spiegel.de",
        "password": "HcIdrMU"
    },
    {
        "id": 45,
        "first_name": "Wilmar",
        "last_name": "Abreheart",
        "email": "wabreheart18@usgs.gov",
        "password": "FuXAe1mQgt"
    },
    {
        "id": 46,
        "first_name": "Zared",
        "last_name": "Feehan",
        "email": "zfeehan19@i2i.jp",
        "password": "fbD1d4xya"
    },
    {
        "id": 47,
        "first_name": "Brittaney",
        "last_name": "Glasscock",
        "email": "bglasscock1a@tripadvisor.com",
        "password": "1T5Gzj"
    },
    {
        "id": 48,
        "first_name": "Edi",
        "last_name": "Cyseley",
        "email": "ecyseley1b@about.me",
        "password": "TSXLNq"
    },
    {
        "id": 49,
        "first_name": "Ariel",
        "last_name": "Riddeough",
        "email": "ariddeough1c@youtube.com",
        "password": "rxHyskiFUq3"
    },
    {
        "id": 50,
        "first_name": "Celestia",
        "last_name": "Brevetor",
        "email": "cbrevetor1d@xing.com",
        "password": "pNbFzqSO"
    },
    {
        "id": 51,
        "first_name": "Roco",
        "last_name": "Labrador",
        "email": "roco@mail.com",
        "password": "123456"
    }
]